{
    "data": [{
            "Intent": "About PD Psychosis",
            "patterns": [
                "About PD disease",
                "Parkinsons Disease",
                "Parkinson Diseases",
                "Parkinson's Disease",
                "Parkinson's Diseases",
                "PDP",
                "About Parkinson Disease Psychosis",
                "About Parkinson's Disease Psychosis",
                "About Parkinsons Disease Psychosis",
                "About Parkinson Diseases Psychosis",
                "About Parkinson's Diseases Psychosis",
                "About Parkinsons Diseases Psychosis",
                "symptoms & potential causes",
                "symptoms & potential cause",
                "Parkinson Disease",
                "Parkinson's Disease",
                "Parkinsons Diseases",
                "Parkinson",
                "Parkinson's",
                "Parkinsons",
                "PD",
                "psychosis",
                "PD Psychosis",
                "Parkinson’s Disease Psychosis",
                "Hallucinations",
                "Visual hallucinations",
                "PD related Hallucinations and Delusions",
                "Delusions of jealousy",
                "Delusions jealousy"
            ],
            "responses": [
                "About Parkinson's Disease Psychosis"
            ]
        },
        {
            "Intent": "About Hallucinations and Delusions",
            "patterns": [
                "Hallucination",
                "Hallucinations",
                "Delusion",
                "Delusions",
                "symptom",
                "symptoms",
                "Parkinson symptoms",
                "Parkinson symptom",
                "Parkinson's symptoms",
                "Parkinson's symptom",
                "Parkinsons symptoms",
                "Parkinsons symptom",
                "Parkinson's symptoms",
                "Parkinson's symptom",
                "symptoms Parkinson",
                "symptom Parkinson",
                "symptoms Parkinson's",
                "symptom Parkinson's",
                "symptoms Parkinson's",
                "symptom Parkinson's",
                "symptoms Parkinsons",
                "symptom Parkinsons",
                "symptoms PD",
                "symptom PD",
                "PD symptom",
                "PD symptoms",
                "symptoms PDP",
                "symptom PDP",
                "PDP symptoms",
                "PDP symptom"
            ],
            "responses": [
                "About Hallucinations & Delusions"
            ]
        },
        {
            "Intent": "About NUPLAZID",
            "patterns": [
                "about NUPLAZID",
                "learn about NUPLAZID",
                "NUPLAZID medications",
                "NUPLAZID Parkinson's",
                "NUPLAZID Parkinson",
                "NUPLAZID Parkinsons",
                "NUPLAZID indication",
                "NUPLAZID indications",
                "indication",
                "indications",
                "indication NUPLAZID",
                "indications NUPLAZID",
                "Learn NUPLAZID",
                "NUPLAZID"
            ],
            "responses": [
                "Learn about NUPLAZID"
            ]
        },
        {
            "Intent": "About NUPLAZID",
            "patterns": [
                "NUPLAZID Discussion guide",
                "NUPLAZID Discussion guides",
                "NUPLAZID Resources",
                "NUPLAZID Resource",
                "Resources NUPLAZID",
                "NUPLAZID Factsheet",
                "Blackbox warning",
                "Blackbox warnings",
                "Warning Blackbox",
                "Warnings Blackbox",
                "Blackbox",
                "Fact sheets & Discussion guide",
                "Fact sheets & Discussion guides",
                "Fact sheet",
                "Factsheet",
                "Factsheets",
                "Fact sheets",
                "Distribution Fact sheet",
                "Distribution Factsheet",
                "Distribution Fact sheets",
                "Fact sheet Distribution",
                "Fact sheet Distributions",
                "Factsheet Distribution",
                "Factsheet Distributions",
                "download Fact sheet",
                "download Factsheet",
                "download Fact sheets",
                "download Factsheets",
                "Factsheet download",
                "Fact sheet download",
                "Distance education fact sheet",
                "Distance education factsheet",
                "Distance education fact sheets",
                "Distance education factsheets",
                "Education Fact sheet",
                "Education Factsheet",
                "Education Fact sheets",
                "Education Factsheets"
            ],
            "responses": [
                "Fact sheets & Discussion guide"
            ]
        },
        {
            "Intent": "Efficacy Story",
            "patterns": [
                "NUPLAZID patient information",
                "NUPLAZID patient informations",
                "FDA NUPLAZID",
                "NUPLAZID pharmacology",
                "FDA approve",
                "NUPLAZID FDA approved",
                "NUPLAZID approved FDA",
                "approved FDA",
                "NUPLAZID approved",
                "FDA approved",
                "motor functions",
                "motor function",
                "Impact on motor functions",
                "Impact motor functions"
            ],
            "responses": [
                "NUPLAZID FDA-approved therapy"
            ]
        },
        {
            "Intent": "NUPLAZID Warnings",
            "patterns": [
                "NUPLAZID warnings",
                "NUPLAZID warning",
                "NUPLAZID precaution",
                "NUPLAZID warning and precaution",
                "NUPLAZID precautions",
                "NUPLAZID warning and precautions",
                "warnings",
                "warning",
                "precaution",
                "precautions",
                "QT Interval",
                "QT Interval Prolongation",
                "QT Interval Prolongations",
                "QT Prolongation",
                "QT Prolongations",
                "interval",
                "Prolongation",
                "Prolongations",
                "QT"
            ],
            "responses": [
                "NUPLAZID Warnings"
            ]
        },
        {
            "Intent": "Efficacy Story",
            "patterns": [
                "NUPLAZID efficacy",
                "Efficacy Data",
                "Efficacy Data NUPLAZID",
                "NUPLAZID primary endpoint",
                "NUPLAZID secondary endpoint",
                "primary endpoint",
                "secondary endpoint",
                "Efficacy NUPLAZID",
                "Efficacy",
                "measuring efficacy",
                "efficacy measuring",
                "measuring"
            ],
            "responses": [
                "NUPLAZID efficacy"
            ]
        },
        {
            "Intent": "Efficacy",
            "patterns": [
                "NUPLAZID efficacy results",
                "NUPLAZID efficacy result",
                "efficacy result",
                "efficacy results"
            ],
            "responses": [
                "NUPLAZID efficacy results"
            ]
        },
        {
            "Intent": "Efficacy",
            "patterns": [
                "OLE",
                "open label safety",
                "Open label extension"
            ],
            "responses": [
                "OLE"
            ]
        },
        {
            "Intent": "Efficacy",
            "patterns": [
                "OLE Study",
                "Open label extension Study",
                "open label safety study",
                "open label study"
            ],
            "responses": [
                "OLE study"
            ]
        },
        {
            "Intent": "About SAPS-PD",
            "patterns": [
                "SAPS-PD",
                "pivotal trial",
                "hallucinations measured",
                "delusion measured",
                "example of SAPS",
                "SAPS PD"
            ],
            "responses": [
                "About SAPS-PD"
            ]
        },
        {
            "Intent": "About SAPS-PD",
            "patterns": [
                "common adverse reactions",
                "common adverse reaction",
                "Adverse reaction",
                "Adverse reactions",
                "Adverse",
                "Common Adverse"
            ],
            "responses": [
                "Adverse reaction"
            ]
        },
        {
            "Intent": "Safety Information",
            "patterns": [
                "Pimavanserin safety",
                "Safety profile",
                "Adverse reactions table",
                "Long Term Safety"
            ],
            "responses": [
                "Pimavanserin safety"
            ]
        },
        {
            "Intent": "Safety Information",
            "patterns": [
                "placebo controlled studies",
                "percentage of suffering",
                "NUPLAZID important safety information",
                "NUPLAZID Safety",
                "NUPLAZID safe",
                "treatment emergent",
                "safety information",
                "safety",
                "dementia",
                "dementia related psychosis",
                "dementia psychosis",
                "Contraindication",
                "tolerability"
            ],
            "responses": [
                "NUPLAZID important safety information"
            ]
        },
        {
            "Intent": "Proposed Moa Information",
            "patterns": [
                "withdrawal from NUPLAZID",
                "Mechanism Of Action",
                "About MOA",
                "MOA",
                "Serotonergic agent",
                "Serotonergic",
                "In Vitro",
                "Vitro",
                "Mechanism of action",
                "Mechanism action"
            ],
            "responses": [
                "About MOA"
            ]
        },
        {
            "Intent": "Dosing",
            "patterns": [
                "timetake NUPLAZID",
                "Dosing Information",
                "dosage and administration",
                "Dosage Administration",
                "administration information",
                "best practices",
                "best practice",
                "NUPLAZID administration",
                "administration NUPLAZID",
                "NUPLAZID dosage",
                "dosage information",
                "dosage details",
                "dosage detail",
                "dosage",
                "administration",
                "sprinkle dosing guide",
                "recommended dosage",
                "recommended daily dosage",
                "daily dosage",
                "Dosage forms",
                "Tablet",
                "Capsule",
                "sprinkled"
            ],
            "responses": [
                "Dosage Administration"
            ]
        },
        {
            "Intent": "Drug Interaction",
            "patterns": [
                "Drug Interaction",
                "Drug Interactions",
                "Drug"
            ],
            "responses": [
                "Drug Interaction"
            ]
        },
        {
            "Intent": "Acadia Connect",
            "patterns": [
                "Acadia Connect patient assistance program",
                "NUPLAZID financial assistance",
                "NUPLAZID financial assistance coverage",
                "NUPLAZID discount card",
                "longtermcareaccess",
                "NUPLAZID foundation assistance",
                "NUPLAZID medication payment assistance",
                "patient care Offered",
                "coverage financial assistance",
                "Guidelines care coordinator",
                "Acadia connect contact information",
                "Formulary Lookup",
                "Prior authorization",
                "Treatment Forms"
            ],
            "responses": [
                "NUPLAZID medication payment assistance"
            ]
        },
        {
            "Intent": "Cost Information",
            "patterns": [
                "NUPLAZID bridge form",
                "Acadia Connect",
                "Connect Acadia",
                "cost and insurance",
                "forms",
                "covering prescription costs",
                "enrolled eligibility"
            ],
            "responses": [
                "cost and insurance"
            ]
        },
        {
            "Intent": "Coverage high level information and links",
            "patterns": [
                "NUPLAZID patient assistance",
                "Treatment form",
                "patient treatment form",
                "free supply",
                "get NUPLAZID"
            ],
            "responses": [
                "NUPLAZID patient assistance"
            ]
        },
        {
            "Intent": "Coverage high level information and links",
            "patterns": [
                "NUPLAZID registry",
                "enroll patient"
            ],
            "responses": [
                "NUPLAZID registry"
            ]
        },
        {
            "Intent": "Coverage high level information and links",
            "patterns": [
                "Insurance Coverage",
                "Insurance Lookup",
                "coverage samples",
                "reimbursement support",
                "medical necessity template",
                "free samples",
                "free sample",
                "medicare plan",
                "Insurance Coverage",
                "patient eligibility",
                "Insurance Options",
                "order sample",
                "order samples",
                "order samples now",
                "order sample now",
                "samples free",
                "order some samples",
                "order some sample",
                "NUPLAZID sample",
                "NUPLAZID samples",
                "sample NUPLAZID",
                "samples NUPLAZID",
                "Samples",
                "sample ordering",
                "sample order"
            ],
            "responses": [
                "Insurance Coverage"
            ]
        },
        {
            "Intent": "Getting NUPLAZID",
            "patterns": [
                "medicine NUPLAZID",
                "NUPLAZID cost",
                "much NUPLAZID",
                "NUPLAZID enrollment form",
                "NUPLAZID drug classification",
                "NUPLAZID black box warning",
                "NUPLAZID pharmacy",
                "prescription process",
                "In-office care",
                "In office care",
                "support documents",
                "reimbursement process",
                "free cost NUPLAZID",
                "free supply",
                "free cost"
            ],
            "responses": [
                "NUPLAZID cost details"
            ]
        },
        {
            "Intent": "Long-Term Care Service",
            "patterns": [
                "Long-term",
                "Long term",
                "Long-term care",
                "Long term care",
                "long term care facility",
                "long-term care facility",
                "long term care facilities",
                "long-term care facilities",
                "long-term service",
                "long term service",
                "long-term care service request",
                "long term care service request",
                "long-term care service request form",
                "long term care service request form"
            ],
            "responses": [
                "Long-Term Care Service"
            ]
        },
        {
            "Intent": "Diagnostic Codes Information and Link",
            "patterns": [
                "ICD-10 Codes",
                "ICD-10 Code",
                "ICD-10",
                "Diagnostic codes",
                "Diagnostic code"
            ],
            "responses": [
                "Diagnostic codes"
            ]
        },
        {
            "Intent": "Resources",
            "patterns": [
                "ICD-10 Codes",
                "ICD-10 Code",
                "ICD-10",
                "Diagnostic codes",
                "Diagnostic code",
                "Dosing Guide",
                "Pricing guide",
                "Service request form",
                "Brochure",
                "Patient Video"
            ],
            "responses": [
                "Resources"
            ]
        },
        {
            "Intent": "Service Request Form",
            "patterns": [
                "letter of appeal",
                "appeal letter",
                "medical necessity",
                "necessity medical"
            ],
            "responses": [
                "General information about authorization"
            ]
        },
        {
            "Intent": "Medical Questions",
            "patterns": [
                "Reporting Adverse reactions",
                "Reporting",
                "Issues",
                "Problem",
                "Concerns",
                "Death",
                "Medical problem",
                "Product issue"
            ],
            "responses": [
                "Medical Questions"
            ]
        },
        {
            "Intent": "General Information",
            "patterns": [
                "placebo-controlled studies",
                "placebo controlled studies",
                "placebo controlled study",
                "placebo controlled",
                "placebo study",
                "placebo control",
                "placebo"
            ],
            "responses": [
                "Placebo controlled studies"
            ]
        },
        {
            "Intent": "Acadia Connect Representative Contact Details",
            "patterns": [
                "NUPLAZID copay assistance",
                "NUPLAZID contact number",
                "NUPLAZID ASSISTANCE",
                "Contact Information",
                "Contact number",
                "Contact details",
                "About ACADIA",
                "Acadiaconnect details"
            ],
            "responses": [
                "Acadiaconnect details"
            ]
        }
    ]
}